steam_api_pkg/__init__.py
steam_api_pkg/steam_user.py
steam_api_pkg-0.1.2.dist-info/licenses/LICENSE.txt
steam_api_pkg-0.1.2.dist-info/METADATA
steam_api_pkg-0.1.2.dist-info/WHEEL
steam_api_pkg-0.1.2.dist-info/top_level.txt
steam_api_pkg-0.1.2.dist-info/RECORD
