Metadata-Version: 2.4
Name: steam_api_pkg
Version: 0.1.2
Summary: A basic package to interface with the Steam API.
Author: Veli Ristimaki
License-Expression: MIT
Keywords: steam,api
Classifier: Programming Language :: Python :: 3
Classifier: Programming Language :: Python :: 3.8
Classifier: Operating System :: OS Independent
Requires-Python: >=3.8
License-File: LICENSE.txt
Requires-Dist: requests
Dynamic: license-file
